{
  "count": "1",
  "encounter_type": "consult_beneficiaries",
  "form_version": "0.0.1",
  "entity_id": "",
  "metadata": {
    "start": {
      "openmrs_entity_parent": "",
      "openmrs_entity": "concept",
      "openmrs_data_type": "start",
      "openmrs_entity_id": "163137AAAAAAAAAAAAAAAAAAAAAAAAAAAAAA"
    },
    "end": {
      "openmrs_entity_parent": "",
      "openmrs_entity": "concept",
      "openmrs_data_type": "end",
      "openmrs_entity_id": "163138AAAAAAAAAAAAAAAAAAAAAAAAAAAAAA"
    },
    "today": {
      "openmrs_entity_parent": "",
      "openmrs_entity": "encounter",
      "openmrs_entity_id": "encounter_date"
    },
    "deviceid": {
      "openmrs_entity_parent": "",
      "openmrs_entity": "concept",
      "openmrs_data_type": "deviceid",
      "openmrs_entity_id": "163149AAAAAAAAAAAAAAAAAAAAAAAAAAAAAA"
    },
    "subscriberid": {
      "openmrs_entity_parent": "",
      "openmrs_entity": "concept",
      "openmrs_data_type": "subscriberid",
      "openmrs_entity_id": "163150AAAAAAAAAAAAAAAAAAAAAAAAAAAAAA"
    },
    "simserial": {
      "openmrs_entity_parent": "",
      "openmrs_entity": "concept",
      "openmrs_data_type": "simserial",
      "openmrs_entity_id": "163151AAAAAAAAAAAAAAAAAAAAAAAAAAAAAA"
    },
    "phonenumber": {
      "openmrs_entity_parent": "",
      "openmrs_entity": "concept",
      "openmrs_data_type": "phonenumber",
      "openmrs_entity_id": "163152AAAAAAAAAAAAAAAAAAAAAAAAAAAAAA"
    },
    "encounter_location": ""
  },
  "step1": {
    "title": "Consult Beneficiaries",
    "display_back_button": true,
    "fields": [
      {
        "key": "consult_beneficiaries",
        "openmrs_entity_parent": "",
        "openmrs_entity": "",
        "openmrs_entity_id": "",
        "type": "native_radio",
        "label": "Did you consult beneficiaries during your visit?",
        "options": [
          {
            "key": "yes",
            "text": "Yes"
          },
          {
            "key": "no",
            "text": "No"
          }
        ],
        "v_required": {
          "value": true,
          "err": "Field required"
        }
      },
      {
        "key": "consult_beneficiaries_consulted_with",
        "openmrs_entity_parent": "",
        "openmrs_entity": "",
        "openmrs_entity_id": "",
        "type": "edit_text",
        "hint": "Describe who you consulted with",
        "relevance": {
          "step1:consult_beneficiaries": {
            "type": "string",
            "ex": "equalTo(., \"yes\")"
          }
        },
        "v_required": {
          "value": true,
          "err": "Field required"
        }
      },
      {
        "key": "consult_beneficiaries_issues_raised",
        "openmrs_entity_parent": "",
        "openmrs_entity": "",
        "openmrs_entity_id": "",
        "type": "edit_text",
        "hint": "What issues were raised?",
        "relevance": {
          "step1:consult_beneficiaries": {
            "type": "string",
            "ex": "equalTo(., \"yes\")"
          }
        },
        "v_required": {
          "value": true,
          "err": "Field required"
        }
      },
      {
        "key": "consult_beneficiaries_flag",
        "openmrs_entity_parent": "",
        "openmrs_entity": "",
        "openmrs_entity_id": "",
        "type": "native_radio",
        "label": "Should you raise a flag for the issues raised?",
        "options": [
          {
            "key": "yes",
            "text": "Yes"
          },
          {
            "key": "no",
            "text": "No"
          }
        ],
        "v_required": {
          "value": true,
          "err": "Field required"
        },
        "relevance": {
          "step1:consult_beneficiaries": {
            "type": "string",
            "ex": "equalTo(., \"yes\")"
          }
        }
      }
    ]
  }
}